aws_recommendation/__init__.py
aws_recommendation/cloudwatch.py
aws_recommendation/cost_estimations.py
aws_recommendation/dynamodb.py
aws_recommendation/ebs.py
aws_recommendation/ec2.py
aws_recommendation/elb.py
aws_recommendation/kms.py
aws_recommendation/rds.py
aws_recommendation/redshift.py
aws_recommendation/s3.py
aws_recommendation/truted_advisor.py
aws_recommendation/utils.py
aws_recommendation-0.3.6.dist-info/LICENCE
aws_recommendation-0.3.6.dist-info/METADATA
aws_recommendation-0.3.6.dist-info/WHEEL
aws_recommendation-0.3.6.dist-info/top_level.txt
aws_recommendation-0.3.6.dist-info/RECORD
