Metadata-Version: 2.1
Name: aws-recommendation
Version: 0.3.6
Summary: Provides AWS recommendations
Author-email: "dheeraj.banodha" <dheerajmbanodha@gmail.com>
Classifier: Programming Language :: Python :: 3
Classifier: Operating System :: OS Independent
Requires-Python: >=3.7
License-File: LICENCE
Requires-Dist: boto3
Requires-Dist: pytz
